odoo/addons/l10n_br_account_payment_order/README.rst
odoo/addons/l10n_br_account_payment_order/__init__.py
odoo/addons/l10n_br_account_payment_order/__manifest__.py
odoo/addons/l10n_br_account_payment_order/constants.py
odoo/addons/l10n_br_account_payment_order/data/boleto_data.xml
odoo/addons/l10n_br_account_payment_order/data/cnab_data.xml
odoo/addons/l10n_br_account_payment_order/data/l10n_br_payment_export_type.xml
odoo/addons/l10n_br_account_payment_order/data/cnab_codes/banco_ailos_240_boleto_discount_code.xml
odoo/addons/l10n_br_account_payment_order/data/cnab_codes/banco_ailos_240_boleto_protest_code.xml
odoo/addons/l10n_br_account_payment_order/data/cnab_codes/banco_ailos_cnab_240.xml
odoo/addons/l10n_br_account_payment_order/data/cnab_codes/banco_bradesco_240_boleto_discount_code.xml
odoo/addons/l10n_br_account_payment_order/data/cnab_codes/banco_bradesco_240_boleto_protest_code.xml
odoo/addons/l10n_br_account_payment_order/data/cnab_codes/banco_bradesco_400_boleto_fee_code.xml
odoo/addons/l10n_br_account_payment_order/data/cnab_codes/banco_bradesco_boleto_wallet_code.xml
odoo/addons/l10n_br_account_payment_order/data/cnab_codes/banco_bradesco_cnab_240_400.xml
odoo/addons/l10n_br_account_payment_order/data/cnab_codes/banco_cef_240_boleto_discount_code.xml
odoo/addons/l10n_br_account_payment_order/data/cnab_codes/banco_cef_240_boleto_fee_code.xml
odoo/addons/l10n_br_account_payment_order/data/cnab_codes/banco_cef_240_boleto_protest_code.xml
odoo/addons/l10n_br_account_payment_order/data/cnab_codes/banco_cef_cnab_240.xml
odoo/addons/l10n_br_account_payment_order/data/cnab_codes/banco_do_brasil_240_boleto_discount_code.xml
odoo/addons/l10n_br_account_payment_order/data/cnab_codes/banco_do_brasil_240_boleto_protest_code.xml
odoo/addons/l10n_br_account_payment_order/data/cnab_codes/banco_do_brasil_400_boleto_fee_code.xml
odoo/addons/l10n_br_account_payment_order/data/cnab_codes/banco_do_brasil_400_boleto_interest_code.xml
odoo_addon_l10n_br_account_payment_order-16.0.9.0.1.dist-info/METADATA
odoo_addon_l10n_br_account_payment_order-16.0.9.0.1.dist-info/WHEEL
odoo_addon_l10n_br_account_payment_order-16.0.9.0.1.dist-info/top_level.txt
odoo_addon_l10n_br_account_payment_order-16.0.9.0.1.dist-info/RECORD
