Metadata-Version: 2.1
Name: odoo-addon-l10n_br_account_payment_order
Version: 16.0.9.0.1
Requires-Python: >=3.10
Requires-Dist: erpbrasil.base
Requires-Dist: odoo-addon-account_due_list_payment_mode>=16.0dev,<16.1dev
Requires-Dist: odoo-addon-account_payment_order>=16.0dev,<16.1dev
Requires-Dist: odoo-addon-l10n_br_account_due_list>=16.0dev,<16.1dev
Requires-Dist: odoo-addon-l10n_br_base>=16.0dev,<16.1dev
Requires-Dist: odoo>=16.0a,<16.1dev
Summary: Brazilian Payment Order
Home-page: https://github.com/OCA/l10n-brazil
License: AGPL-3
Author: KMEE, Akretion, Odoo Community Association (OCA)
Author-email: support@odoo-community.org
Classifier: Programming Language :: Python
Classifier: Framework :: Odoo
Classifier: Framework :: Odoo :: 16.0
Classifier: License :: OSI Approved :: GNU Affero General Public License v3
Classifier: Development Status :: 4 - Beta
